btrade_api_client/__init__.py
btrade_api_client/auth.py
btrade_api_client/cli.py
btrade_api_client/client.py
btrade_api_client-0.2.7.dist-info/LICENSE
btrade_api_client-0.2.7.dist-info/METADATA
btrade_api_client-0.2.7.dist-info/WHEEL
btrade_api_client-0.2.7.dist-info/top_level.txt
btrade_api_client-0.2.7.dist-info/RECORD
