Metadata-Version: 2.1
Name: btrade-api-client
Version: 0.2.7
Summary: BTrade API client
Home-page: https://bitbucket.org/bittradeaustralia/btrade-api-client/src/master/
Author: Niels Draaisma
Author-email: ndraaisma@btrade.io
License: UNKNOWN
Download-URL: https://bitbucket.org/bittradeaustralia/btrade-api-client/get/master.zip
Project-URL: API Documentation, https://btrade.io/api/
Platform: UNKNOWN
Classifier: Development Status :: 5 - Production/Stable
Classifier: Programming Language :: Python
Classifier: Intended Audience :: Developers
Requires-Dist: pygments
Requires-Dist: requests
